ncc_cli/__init__.py
ncc_cli/ncc_cli.py
ncc_cli-0.0.6.dist-info/LICENSE.md
ncc_cli-0.0.6.dist-info/METADATA
ncc_cli-0.0.6.dist-info/WHEEL
ncc_cli-0.0.6.dist-info/entry_points.txt
ncc_cli-0.0.6.dist-info/top_level.txt
ncc_cli-0.0.6.dist-info/RECORD
