Metadata-Version: 2.1
Name: ncc-cli
Version: 0.0.6
Summary: A small command-line client for NextCloud/ownCloud
Home-page: https://github.com/jdhirst1/ncc_cli
Author: James Hirst
Author-email: jdhirst@hirstgroup.net
License: UNKNOWN
Platform: UNKNOWN
Classifier: Programming Language :: Python :: 3.8
Classifier: License :: OSI Approved :: GNU General Public License v3 (GPLv3)
Classifier: Operating System :: OS Independent
Requires-Dist: humanize
Requires-Dist: pyocclient
Requires-Dist: texttable
Requires-Dist: tqdm
Requires-Dist: yaspin
